{
  "users": [
    {
      "id": "cb92",
      "companyName": "Company",
      "companyAddress": "address street 123",
      "contactNumber": "01111977933",
      "email": "email@gmail.com",
      "username": "companyname",
      "password": "namecompany"
    },
    {
      "id": "0a9c",
      "companyName": "company",
      "companyAddress": "com address",
      "contactNumber": "012313213",
      "email": "company@gmail.com",
      "username": "company123",
      "password": "companypass"
    }
  ]
}